odoo/addons/account_payment_unece/README.rst
odoo/addons/account_payment_unece/__init__.py
odoo/addons/account_payment_unece/__manifest__.py
odoo/addons/account_payment_unece/data/account_payment_method.xml
odoo/addons/account_payment_unece/data/unece.xml
odoo/addons/account_payment_unece/i18n/account_payment_unece.pot
odoo/addons/account_payment_unece/i18n/de.po
odoo/addons/account_payment_unece/i18n/es.po
odoo/addons/account_payment_unece/i18n/fr.po
odoo/addons/account_payment_unece/i18n/hr.po
odoo/addons/account_payment_unece/i18n/it.po
odoo/addons/account_payment_unece/models/__init__.py
odoo/addons/account_payment_unece/models/account_payment_method.py
odoo/addons/account_payment_unece/models/unece_code_list.py
odoo/addons/account_payment_unece/readme/CONFIGURE.md
odoo/addons/account_payment_unece/readme/CONTRIBUTORS.md
odoo/addons/account_payment_unece/readme/DESCRIPTION.md
odoo/addons/account_payment_unece/static/description/icon.png
odoo/addons/account_payment_unece/static/description/index.html
odoo/addons/account_payment_unece/views/account_payment_method.xml
odoo/addons/account_payment_unece/views/unece_code_list.xml
odoo_addon_account_payment_unece-18.0.1.0.0.5.dist-info/METADATA
odoo_addon_account_payment_unece-18.0.1.0.0.5.dist-info/WHEEL
odoo_addon_account_payment_unece-18.0.1.0.0.5.dist-info/top_level.txt
odoo_addon_account_payment_unece-18.0.1.0.0.5.dist-info/RECORD
