Metadata-Version: 2.1
Name: odoo-addon-account_payment_unece
Version: 18.0.1.0.0.5
Requires-Python: >=3.10
Requires-Dist: odoo-addon-account_payment_method_base==18.0.*
Requires-Dist: odoo-addon-base_unece==18.0.*
Requires-Dist: odoo==18.0.*
Summary: UNECE nomenclature for the payment methods
Home-page: https://github.com/OCA/community-data-files
License: AGPL-3
Author: Akretion,Odoo Community Association (OCA)
Author-email: support@odoo-community.org
Classifier: Programming Language :: Python
Classifier: Framework :: Odoo
Classifier: Framework :: Odoo :: 18.0
Classifier: License :: OSI Approved :: GNU Affero General Public License v3
